physicsml/__init__.py
physicsml/py.typed
physicsml/utils.py
physicsml/version.py
physicsml/backends/__init__.py
physicsml/backends/backend_selector.py
physicsml/backends/openeye_backend.py
physicsml/backends/rdkit_backend.py
physicsml/featurisation/__init__.py
physicsml/featurisation/physicsml_features/atom_features.py
physicsml/featurisation/physicsml_features/bond_features.py
physicsml/featurisation/physicsml_features/physicsml_features.py
physicsml/lightning/__init__.py
physicsml/lightning/config.py
physicsml/lightning/datamodule.py
physicsml/lightning/model.py
physicsml/lightning/model_uncertainty.py
physicsml/lightning/module.py
physicsml/lightning/pre_batching_in_memory.py
physicsml/lightning/pre_batching_on_disk.py
physicsml/lightning/graph_datasets/__init__.py
physicsml/lightning/graph_datasets/graph_dataset.py
physicsml/lightning/graph_datasets/neighbourhood_list_torch.py
physicsml/lightning/graph_datasets/torch_nl_vendored/__init__.py
physicsml/lightning/graph_datasets/torch_nl_vendored/geometry.py
physicsml/lightning/graph_datasets/torch_nl_vendored/linked_cell.py
physicsml/lightning/graph_datasets/torch_nl_vendored/naive_impl.py
physicsml/lightning/graph_datasets/torch_nl_vendored/neighbor_list.py
physicsml/lightning/graph_datasets/torch_nl_vendored/timer.py
physicsml/lightning/graph_datasets/torch_nl_vendored/utils.py
physicsml/lightning/losses/__init__.py
physicsml/lightning/losses/construct_loss.py
physicsml/lightning/losses/loss_base.py
physicsml/lightning/losses/masked_mse_loss.py
physicsml/lightning/losses/multitask_losses.py
physicsml/lightning/losses/serial_bce_w_logits_loss.py
physicsml/lightning/losses/stock_losses.py
physicsml/lightning/losses/weighted_mse_loss.py
physicsml/models/__init__.py
physicsml/models/prism.py
physicsml/models/utils.py
physicsml/models/allegro/__init__.py
physicsml/models/allegro/allegro_prism.py
physicsml/models/allegro/mean_var/__init__.py
physicsml/models/allegro/mean_var/default_configs.py
physicsml-0.6.0.dist-info/LICENSE
physicsml-0.6.0.dist-info/METADATA
physicsml-0.6.0.dist-info/WHEEL
physicsml-0.6.0.dist-info/entry_points.txt
physicsml-0.6.0.dist-info/top_level.txt
physicsml-0.6.0.dist-info/RECORD
