Metadata-Version: 2.1
Name: physicsml
Version: 0.6.0
Summary: A package for all physics based/related models
Author: Exscientia
Maintainer: Exscientia
Project-URL: documentation, https://exscientia.github.io/physicsml/
Project-URL: repository, https://github.com/exscientia/physicsml.git
Project-URL: issue-tracker, https://github.com/exscientia/physicsml/issues
Project-URL: changelog, https://github.com/exscientia/physicsml/src/main/CHANGELOG.md
Classifier: Development Status :: 4 - Beta
Classifier: Intended Audience :: Science/Research
Classifier: Natural Language :: English
Classifier: Operating System :: OS Independent
Classifier: Programming Language :: Python
Classifier: Programming Language :: Python :: 3 :: Only
Classifier: Programming Language :: Python :: 3.10
Classifier: Programming Language :: Python :: 3.11
Classifier: Typing :: Typed
Requires-Python: >=3.10
License-File: LICENSE
Requires-Dist: molflux[lightning] >=0.5.0
Requires-Dist: torch-geometric >=2.5.0
Requires-Dist: e3nn
Requires-Dist: torchani !=2.2.4
Provides-Extra: ase
Requires-Dist: rdkit ; extra == 'ase'
Requires-Dist: ase ; extra == 'ase'
Provides-Extra: dev
Requires-Dist: nox[uv] ; extra == 'dev'
Requires-Dist: pre-commit ; extra == 'dev'
Provides-Extra: docs
Requires-Dist: sphinx !=5.1.0 ; extra == 'docs'
Requires-Dist: sphinx-sitemap ; extra == 'docs'
Requires-Dist: sphinx-inline-tabs ; extra == 'docs'
Requires-Dist: sphinx-book-theme ; extra == 'docs'
Requires-Dist: sphinx-design ; extra == 'docs'
Requires-Dist: sphinx-toolbox ; extra == 'docs'
Requires-Dist: sphinx-togglebutton ; extra == 'docs'
Requires-Dist: jupytext >=1.11.2 ; extra == 'docs'
Requires-Dist: myst-nb ; extra == 'docs'
Requires-Dist: ipywidgets ; extra == 'docs'
Requires-Dist: rdkit >=2023.9.1 ; extra == 'docs'
Requires-Dist: matplotlib ; extra == 'docs'
Requires-Dist: ase ; extra == 'docs'
Provides-Extra: openeye
Requires-Dist: openeye-toolkits ; extra == 'openeye'
Provides-Extra: openmm
Requires-Dist: rdkit ; extra == 'openmm'
Provides-Extra: rdkit
Requires-Dist: rdkit ; extra == 'rdkit'
Provides-Extra: tests
Requires-Dist: coverage[toml] ; extra == 'tests'
Requires-Dist: coverage-badge ; extra == 'tests'
Requires-Dist: pytest ; extra == 'tests'
Requires-Dist: h5py ; extra == 'tests'
Provides-Extra: typing
Requires-Dist: mypy ; extra == 'typing'
Requires-Dist: types-PyYAML ; extra == 'typing'
Requires-Dist: types-setuptools ; extra == 'typing'
